MANIFEST.in
readme.md
setup.py
benchmark/__init__.py
benchmark/cache_set_benchmark.py
benchmark/compute.py
benchmark/product_db.py
benchmark/utils.py
distcache/__init__.py
distcache/cache_client.py
distcache/cache_server.py
distcache/config.py
distcache/consistent_hashing.py
distcache/health_client.py
distcache/health_server.py
distcache/logger.py
distcache/lru_cache.py
distcache/utils.py
distcache.egg-info/PKG-INFO
distcache.egg-info/SOURCES.txt
distcache.egg-info/dependency_links.txt
distcache.egg-info/top_level.txt
tests/__init__.py
tests/cache.py
tests/global_counter.py
tests/test_heartbeat.py
tests/test_logger.py
tests/test_lru_cache.py
tests/test_network_utils.py
usage/1_client.py
usage/1_server.py
usage/__init__.py
usage/reconstructing_cache.py