Metadata-Version: 2.1
Name: distcache
Version: 0.1.3.1
Summary: Distcache is a python open-source distributed in-memory cache and database.
Home-page: https://github.com/wasimusu/distcache
Author: Wasim Akram Khan
License: MIT License 
Project-URL: Source Code, https://github.com/wasimusu/distcache
Keywords: open-source,cache,distributed-cache,in-memory,database
Platform: UNKNOWN
Classifier: License :: OSI Approved :: MIT License
Classifier: Programming Language :: Python :: 2.7
Classifier: Programming Language :: Python :: 3.5
Classifier: Programming Language :: Python :: 3.7
